main.py
mseep_ragflow_mcp-0.1.6.dist-info/licenses/LICENSE
mseep_ragflow_mcp-0.1.6.dist-info/METADATA
mseep_ragflow_mcp-0.1.6.dist-info/WHEEL
mseep_ragflow_mcp-0.1.6.dist-info/entry_points.txt
mseep_ragflow_mcp-0.1.6.dist-info/top_level.txt
mseep_ragflow_mcp-0.1.6.dist-info/RECORD
